pyqlaw/__init__.py
pyqlaw/_convergence.py
pyqlaw/_elements.py
pyqlaw/_eom.py
pyqlaw/_integrate.py
pyqlaw/_lyapunov.py
pyqlaw/_perturbations.py
pyqlaw/_plot_helper.py
pyqlaw/_plot_methods.py
pyqlaw/_qlaw.py
pyqlaw/_symbolic.py
pyqlaw/_transformations.py
pyqlaw-0.2.3.dist-info/LICENSE
pyqlaw-0.2.3.dist-info/METADATA
pyqlaw-0.2.3.dist-info/WHEEL
pyqlaw-0.2.3.dist-info/top_level.txt
pyqlaw-0.2.3.dist-info/RECORD
