Metadata-Version: 2.1
Name: pyqlaw
Version: 0.2.3
Summary: high-fidelity spaceraft dynamics propagator
Home-page: https://github.com/Yuricst/pyqlaw
Author: Yuri Shimane
Author-email: yuri.shimane@gatech.edu
License: MIT License
Keywords: astrodynamics
Classifier: Programming Language :: Python :: 3.8
Classifier: Programming Language :: Python :: 3.9
Classifier: Programming Language :: Python :: 3.10
Classifier: Programming Language :: Python :: 3.11
Classifier: Programming Language :: Python :: 3.12
Classifier: Programming Language :: Python :: 3.13
Classifier: Programming Language :: Python :: 3.14
License-File: LICENSE
Requires-Dist: sympy>=1.12
Requires-Dist: numpy>=1.20.4
Requires-Dist: numba>=0.54.0
Requires-Dist: matplotlib>=3.8.4
Requires-Dist: scipy>=1.13.0
Requires-Dist: tqdm>=4.66.4
Requires-Dist: spiceypy>=5.1.0
